hwpx_mcp/__init__.py
hwpx_mcp/__main__.py
hwpx_mcp/cli.py
hwpx_mcp/config.py
hwpx_mcp/exceptions.py
hwpx_mcp/logging_utils.py
hwpx_mcp/models.py
hwpx_mcp/server.py
hwpx_mcp/services/document_service.py
hwpx_mcp/session.py
hwpx_mcp/user_config.py
hwpx_mcp/workspace.py
hwpx_mcp-0.1.0.dist-info/WHEEL
hwpx_mcp-0.1.0.dist-info/entry_points.txt
hwpx_mcp-0.1.0.dist-info/METADATA
hwpx_mcp-0.1.0.dist-info/RECORD
