Metadata-Version: 2.3
Name: hwpx-mcp
Version: 0.1.0
Summary: python-hwpx 기반 HWPX 자동화를 제공하는 Smithery MCP 서버
Author: HWPX MCP Maintainers
Author-email: HWPX MCP Maintainers <maintainers@example.com>
Requires-Dist: mcp>=1.14.0
Requires-Dist: python-hwpx>=1.3
Requires-Dist: smithery>=0.1.25
Requires-Dist: pydantic>=2.7
Requires-Dist: typer>=0.12.5
Requires-Dist: rich>=13.9
Requires-Dist: tomli-w>=1.0.0
Requires-Dist: tomli>=2.0.1 ; python_full_version < '3.11'
Requires-Dist: pytest>=8.3.3 ; extra == 'dev'
Requires-Dist: pytest-cov>=5.0.0 ; extra == 'dev'
Requires-Python: >=3.10
Provides-Extra: dev
